space_collector/__init__.py
space_collector/killall.py
space_collector/serial2tcp.py
space_collector/game/__init__.py
space_collector/game/add.py
space_collector/game/constants.py
space_collector/game/game.py
space_collector/game/math.py
space_collector/game/planet.py
space_collector/game/player.py
space_collector/game/player_orientations.py
space_collector/game/server.py
space_collector/game/spaceship.py
space_collector/network/__init__.py
space_collector/network/client.py
space_collector/network/data_handler.py
space_collector/network/server.py
space_collector/viewer/__init__.py
space_collector/viewer/__main__.py
space_collector/viewer/animation.py
space_collector/viewer/constants.py
space_collector/viewer/planet.py
space_collector/viewer/player.py
space_collector/viewer/score.py
space_collector/viewer/space_background.py
space_collector/viewer/spaceship.py
space_collector/viewer/utils.py
space_collector/viewer/viewer.py
space_collector/viewer/window.py
space_collector/viewer/images/Sportrop.ttf
space_collector/viewer/images/comet.png
space_collector/viewer/images/high_energy.png
space_collector/viewer/images/high_energy.xcf
space_collector/viewer/images/neon.xcf
space_collector/viewer/images/score_background.png
space_collector/viewer/images/station.png
space_collector/viewer/images/backgrounds/Blue_Nebula_04-1024x1024.png
space_collector/viewer/images/backgrounds/Blue_Nebula_05-1024x1024.png
space_collector/viewer/images/backgrounds/Blue_Nebula_06-1024x1024.png
space_collector/viewer/images/backgrounds/Blue_Nebula_08-1024x1024.png
space_collector/viewer/images/backgrounds/Green_Nebula_01-1024x1024.png
space_collector/viewer/images/backgrounds/Green_Nebula_02-1024x1024.png
space_collector/viewer/images/backgrounds/Green_Nebula_03-1024x1024.png
space_collector/viewer/images/backgrounds/Green_Nebula_04-1024x1024.png
space_collector/viewer/images/backgrounds/Green_Nebula_05-1024x1024.png
space_collector/viewer/images/backgrounds/Green_Nebula_06-1024x1024.png
space_collector-1.2.0.dist-info/licenses/LICENSE
space_collector-1.2.0.dist-info/METADATA
space_collector-1.2.0.dist-info/WHEEL
space_collector-1.2.0.dist-info/top_level.txt
space_collector-1.2.0.dist-info/RECORD
