Metadata-Version: 2.4
Name: space_collector
Version: 1.2.0
Summary: Space collector programming game
Author-email: Vincent Poulailleau <vpoulailleau@gmail.com>
License-Expression: BSD-3-Clause
Project-URL: Source code, https://github.com/vpoulailleau/space_collector
Project-URL: Repository, https://github.com/vpoulailleau/space_collector
Project-URL: Documentation, https://github.com/vpoulailleau/space_collector/README.md
Keywords: space,collector,game
Classifier: Development Status :: 5 - Production/Stable
Classifier: Intended Audience :: Developers
Classifier: Natural Language :: English
Classifier: Programming Language :: Python :: 3
Classifier: Programming Language :: Python :: 3.11
Classifier: Programming Language :: Python :: 3.12
Classifier: Programming Language :: Python :: 3.13
Classifier: Programming Language :: Python :: 3.14
Classifier: Topic :: Utilities
Classifier: Topic :: Games/Entertainment :: Real Time Strategy
Requires-Python: >=3.11
License-File: LICENSE
Requires-Dist: arcade>=3
Requires-Dist: pyserial==3.5
Requires-Dist: psutil>=7.0
Provides-Extra: dev
Requires-Dist: build; extra == "dev"
Requires-Dist: pytest; extra == "dev"
Requires-Dist: pytest-cov; extra == "dev"
Requires-Dist: python-dev-tools>=2023; extra == "dev"
Requires-Dist: pre-commit<4,>=3; extra == "dev"
Requires-Dist: pyinstrument; extra == "dev"
Requires-Dist: twine; extra == "dev"
Dynamic: license-file
